src/timeprinter.v
module timeprinter(pixelclock,hsinc,vsinc,draw,th,tm,ts,pixel);
input pixelclock,hsinc,vsinc,draw,th,tm,ts;
reg [0:14] digit [0:10];
output reg pixel;
parameter boxSize=10;//cuantas veces se va a repetir cada pixel
parameter levelNumber=5;
parameter withNumber=3;
parameter h_whith = 640;
parameter v_whith = 480;
parameter start2draw=1; //numero de filas que espero antes de escrivir el display
parameter d0= 15'b111101101101111;
parameter d1= 15'b001001001001001;
parameter d2= 15'b111001111100111;
parameter d3=15'b111001111001111;
parameter d4=15'b101101111001001;
parameter d5=15'b111100111001111;
parameter d6=15'b111100111101111;
parameter d7=15'b111001111001001;
parameter d8=15'b111101111101111;
parameter d9=15'b111101111001001;
parameter dpuntos=15'b000010000010000;
reg once=1;
reg endPrint=1;
reg [3:0] v_bitCount=0;//repetiziones verticales de cada bit
reg [3:0] h_bitCount=0;//cuenta las repeticiones horizontales
reg [3:0] printingPart=0;//contador de que parte de la line horizontal se esta imprimeinto
reg [3:0] levelPrinting=0;//nivel del numero que se imprime


reg[15:0] h_count=0;//contador de columnas y tambien utilizado para contar pulsos de clocks
reg[15:0] v_count=0;//contador de filas

reg [3:0] thm=5;
reg [3:0] thl=0;

reg [3:0] tmm=3;
reg [3:0] tml=4;

reg [3:0] tsm=1;
reg [3:0] tsl=8;

always @ (posedge pixelclock) begin
    if(once==1)begin
        digit[0]=d0;
        digit[1]=d1;
        digit[2]=d2;
        digit[3]=d3;
        digit[4]=d4;
        digit[5]=d5;
        digit[6]=d6;
        digit[7]=d7;
        digit[8]=d8;
        digit[9]=d9;
        digit[10]=dpuntos;
        once=0;
        $display("memoria");
        $display("%b",digit[0]);
        $display("%b",digit[1]);
        $display("%b",digit[2]);
        $display("%b",digit[3]);
        $display("%b",digit[4]);
        $display("%b",digit[5]);
        $display("%b",digit[6]);
        $display("%b",digit[7]);
        $display("%b",digit[8]);
        $display("%b",digit[9]);
        $display("%b",digit[10]);
        
    end
    if((draw==1) && (v_count>(start2draw-1))&&(v_count<(start2draw+(boxSize*levelNumber)))&&(endPrint==1))begin
        if(h_bitCount<boxSize)begin//si todavia no conte el ancho del pixel mantengo el valor
            pixel=digit[thm][(levelPrinting*withNumber)+printingPart];
            $write("%b",pixel);
            h_bitCount=h_bitCount+1;
           //$write("%d",(levelPrinting*withNumber)+printingPart);
        end else begin
            if(printingPart<(withNumber-1))begin//TODO me parece que iria menos 1 en la condicion
                printingPart=printingPart+1;
            end else begin
                printingPart=0;
                endPrint=0;
            end
        
            h_bitCount=0;
        
        
        
        end
        
        h_count=h_count+1;
    end else begin
        h_count=0;
        pixel=0;
    end
    
end

always @ (posedge hsinc) begin
    v_count=v_count+1;//cada vez que hay un pulso de h sync se incremente al numero de fila
    $display (" ");
     if(v_bitCount<boxSize)begin
       v_bitCount=v_bitCount+1;
        endPrint=1;
       //$display("%d",v_bitCount);
    end else begin
        v_bitCount=0;
        if(levelPrinting<levelNumber)begin
            levelPrinting=levelPrinting+1;
        end else
        levelPrinting=0; 
        

    end
end

always @ (posedge vsinc) begin
    v_count=0;//cada vez que hay un pulso de v sync se reinicia el contador de columnas
   
end



endmodule

src/mmsync.v
module mmsync(pixelClock,h_sync_signal,v_sync_signal,draw);
input wire pixelClock;
output wire h_sync_signal,v_sync_signal,draw;

//**********Caracterisitcas de la pantalla*********************
parameter h_whith = 640; //ancho en pixeles de la pantalla
parameter h_front_porch=16;//tiempo en pixleclocks de el pulso de h sync
parameter h_back_porch=48;
parameter h_sync_pulse=96;

parameter one_row=800;

parameter v_whith = 480;
parameter v_front_porch=10;
parameter v_back_porch=33;
parameter v_sync_pulse=2;
//******fin Caracterisitcas de la pantalla*********************

 reg[15:0] h_count=0;//contador de columnas y tambien utilizado para contar pulsos de clocks
 reg[15:0] v_count=0;//contador de filas
 
 assign h_sync_signal =((h_whith+h_front_porch)<=h_count)&&(h_count<(h_whith+h_front_porch+h_sync_pulse));
 assign v_sync_signal =((v_whith+v_front_porch)<=v_count)&&(v_count<(v_whith+v_front_porch+v_sync_pulse));
 assign draw=(h_count<(h_whith))&&(v_count<v_whith);
always @ (posedge pixelClock) begin
    
    if(h_count==(h_whith+h_front_porch+h_sync_pulse+ h_back_porch)-1) begin
        h_count<=0;
        v_count<=v_count+1;
    end else begin
        h_count<=h_count+1;
    end

    if(v_count==(v_whith+v_front_porch+v_sync_pulse+v_back_porch))begin
        v_count<=0;
    end
end


endmodule

src/mclock.v
`timescale 10ns / 10ns
module clock_gen(clk);

parameter PERIOD = 2;

output reg clk;
	 
always
	begin: MATI
		clk <= 1'b0;
		#(PERIOD/2);
		clk <= 1'b1;
		#(PERIOD/2);
	end
endmodule

src/tstBench.v
module tstBench;
wire clock,hs,vs,d,pix;
 wire[7:0] tth;
 wire[7:0] ttm;
 wire[7:0] tts;
reg reset,start;
clock_gen mclk(clock);
//(pixelClock,h_sync_signal,v_sync_signal,draw);
//module mtimer(clk,reset,ss,th,tm,ts);
//mtimer timer(clock,reset,start,tth,ttm,tts);
mmsync vga_sync (clock,hs,vs,d);
//timeprinter(pixelclock,hsinc,vsinc,draw,th,tm,ts,pixel);
timeprinter printer (clock,hs,vs,d,1,1,1,pix);
  initial begin
    #100000
    $finish;

  end
reg dummy;
  reg[8*64:0] dumpfile_path = "output.vcd";
 initial begin
    dummy = $value$plusargs("VCD_PATH=%s", dumpfile_path);
    $dumpfile(dumpfile_path);
    $dumpvars(0,tstBench);
  end
endmodule

bin/output.vcd
$date
	Mon Nov 12 14:29:18 2018
$end
$version
	Icarus Verilog
$end
$timescale
	10ns
$end
$scope module tstBench $end
$var wire 1 ! clock $end
$var wire 1 " d $end
$var wire 1 # hs $end
$var wire 1 $ pix $end
$var wire 1 % vs $end
$var reg 1 & dummy $end
$var reg 513 ' dumpfile_path [512:0] $end
$scope module mclk $end
$var reg 1 ( clk $end
$scope begin MATI $end
$upscope $end
$upscope $end
$scope module vga_sync $end
$var wire 1 " draw $end
$var wire 1 # h_sync_signal $end
$var wire 1 ! pixelClock $end
$var wire 1 % v_sync_signal $end
$var reg 16 ) h_count [15:0] $end
$var reg 16 * v_count [15:0] $end
$upscope $end
$scope module printer $end
$var wire 1 " draw $end
$var wire 1 # hsinc $end
$var wire 1 ! pixelclock $end
$var wire 1 + th $end
$var wire 1 , tm $end
$var wire 1 - ts $end
$var wire 1 % vsinc $end
$var reg 1 . endPrint $end
$var reg 4 / h_bitCount [3:0] $end
$var reg 16 0 h_count [15:0] $end
$var reg 4 1 levelPrinting [3:0] $end
$var reg 1 2 once $end
$var reg 1 3 pixel $end
$var reg 4 4 printingPart [3:0] $end
$var reg 4 5 thl [3:0] $end
$var reg 4 6 thm [3:0] $end
$var reg 4 7 tml [3:0] $end
$var reg 4 8 tmm [3:0] $end
$var reg 4 9 tsl [3:0] $end
$var reg 4 : tsm [3:0] $end
$var reg 4 ; v_bitCount [3:0] $end
$var reg 16 < v_count [15:0] $end
$upscope $end
$upscope $end
$enddefinitions $end
#0
$dumpvars
b0 <
b0 ;
b1 :
b1000 9
b11 8
b100 7
b101 6
b0 5
b0 4
x3
12
b0 1
b0 0
b0 /
1.
1-
1,
1+
b0 *
b0 )
0(
b110001001101001011011100010111101101111011101010111010001110000011101010111010000101110011101100110001101100100 '
1&
0%
x$
0#
1"
0!
$end
#1
b1 )
03
0$
02
1(
1!
#2
0(
0!
#3
b10 )
1(
1!
#4
0(
0!
#5
b11 )
1(
1!
#6
0(
0!
#7
b100 )
1(
1!
#8
0(
0!
#9
b101 )
1(
1!
#10
0(
0!
#11
b110 )
1(
1!
#12
0(
0!
#13
b111 )
1(
1!
#14
0(
0!
#15
b1000 )
1(
1!
#16
0(
0!
#17
b1001 )
1(
1!
#18
0(
0!
#19
b1010 )
1(
1!
#20
0(
0!
#21
b1011 )
1(
1!
#22
0(
0!
#23
b1100 )
1(
1!
#24
0(
0!
#25
b1101 )
1(
1!
#26
0(
0!
#27
b1110 )
1(
1!
#28
0(
0!
#29
b1111 )
1(
1!
#30
0(
0!
#31
b10000 )
1(
1!
#32
0(
0!
#33
b10001 )
1(
1!
#34
0(
0!
#35
b10010 )
1(
1!
#36
0(
0!
#37
b10011 )
1(
1!
#38
0(
0!
#39
b10100 )
1(
1!
#40
0(
0!
#41
b10101 )
1(
1!
#42
0(
0!
#43
b10110 )
1(
1!
#44
0(
0!
#45
b10111 )
1(
1!
#46
0(
0!
#47
b11000 )
1(
1!
#48
0(
0!
#49
b11001 )
1(
1!
#50
0(
0!
#51
b11010 )
1(
1!
#52
0(
0!
#53
b11011 )
1(
1!
#54
0(
0!
#55
b11100 )
1(
1!
#56
0(
0!
#57
b11101 )
1(
1!
#58
0(
0!
#59
b11110 )
1(
1!
#60
0(
0!
#61
b11111 )
1(
1!
#62
0(
0!
#63
b100000 )
1(
1!
#64
0(
0!
#65
b100001 )
1(
1!
#66
0(
0!
#67
b100010 )
1(
1!
#68
0(
0!
#69
b100011 )
1(
1!
#70
0(
0!
#71
b100100 )
1(
1!
#72
0(
0!
#73
b100101 )
1(
1!
#74
0(
0!
#75
b100110 )
1(
1!
#76
0(
0!
#77
b100111 )
1(
1!
#78
0(
0!
#79
b101000 )
1(
1!
#80
0(
0!
#81
b101001 )
1(
1!
#82
0(
0!
#83
b101010 )
1(
1!
#84
0(
0!
#85
b101011 )
1(
1!
#86
0(
0!
#87
b101100 )
1(
1!
#88
0(
0!
#89
b101101 )
1(
1!
#90
0(
0!
#91
b101110 )
1(
1!
#92
0(
0!
#93
b101111 )
1(
1!
#94
0(
0!
#95
b110000 )
1(
1!
#96
0(
0!
#97
b110001 )
1(
1!
#98
0(
0!
#99
b110010 )
1(
1!
#100
0(
0!
#101
b110011 )
1(
1!
#102
0(
0!
#103
b110100 )
1(
1!
#104
0(
0!
#105
b110101 )
1(
1!
#106
0(
0!
#107
b110110 )
1(
1!
#108
0(
0!
#109
b110111 )
1(
1!
#110
0(
0!
#111
b111000 )
1(
1!
#112
0(
0!
#113
b111001 )
1(
1!
#114
0(
0!
#115
b111010 )
1(
1!
#116
0(
0!
#117
b111011 )
1(
1!
#118
0(
0!
#119
b111100 )
1(
1!
#120
0(
0!
#121
b111101 )
1(
1!
#122
0(
0!
#123
b111110 )
1(
1!
#124
0(
0!
#125
b111111 )
1(
1!
#126
0(
0!
#127
b1000000 )
1(
1!
#128
0(
0!
#129
b1000001 )
1(
1!
#130
0(
0!
#131
b1000010 )
1(
1!
#132
0(
0!
#133
b1000011 )
1(
1!
#134
0(
0!
#135
b1000100 )
1(
1!
#136
0(
0!
#137
b1000101 )
1(
1!
#138
0(
0!
#139
b1000110 )
1(
1!
#140
0(
0!
#141
b1000111 )
1(
1!
#142
0(
0!
#143
b1001000 )
1(
1!
#144
0(
0!
#145
b1001001 )
1(
1!
#146
0(
0!
#147
b1001010 )
1(
1!
#148
0(
0!
#149
b1001011 )
1(
1!
#150
0(
0!
#151
b1001100 )
1(
1!
#152
0(
0!
#153
b1001101 )
1(
1!
#154
0(
0!
#155
b1001110 )
1(
1!
#156
0(
0!
#157
b1001111 )
1(
1!
#158
0(
0!
#159
b1010000 )
1(
1!
#160
0(
0!
#161
b1010001 )
1(
1!
#162
0(
0!
#163
b1010010 )
1(
1!
#164
0(
0!
#165
b1010011 )
1(
1!
#166
0(
0!
#167
b1010100 )
1(
1!
#168
0(
0!
#169
b1010101 )
1(
1!
#170
0(
0!
#171
b1010110 )
1(
1!
#172
0(
0!
#173
b1010111 )
1(
1!
#174
0(
0!
#175
b1011000 )
1(
1!
#176
0(
0!
#177
b1011001 )
1(
1!
#178
0(
0!
#179
b1011010 )
1(
1!
#180
0(
0!
#181
b1011011 )
1(
1!
#182
0(
0!
#183
b1011100 )
1(
1!
#184
0(
0!
#185
b1011101 )
1(
1!
#186
0(
0!
#187
b1011110 )
1(
1!
#188
0(
0!
#189
b1011111 )
1(
1!
#190
0(
0!
#191
b1100000 )
1(
1!
#192
0(
0!
#193
b1100001 )
1(
1!
#194
0(
0!
#195
b1100010 )
1(
1!
#196
0(
0!
#197
b1100011 )
1(
1!
#198
0(
0!
#199
b1100100 )
1(
1!
#200
0(
0!
#201
b1100101 )
1(
1!
#202
0(
0!
#203
b1100110 )
1(
1!
#204
0(
0!
#205
b1100111 )
1(
1!
#206
0(
0!
#207
b1101000 )
1(
1!
#208
0(
0!
#209
b1101001 )
1(
1!
#210
0(
0!
#211
b1101010 )
1(
1!
#212
0(
0!
#213
b1101011 )
1(
1!
#214
0(
0!
#215
b1101100 )
1(
1!
#216
0(
0!
#217
b1101101 )
1(
1!
#218
0(
0!
#219
b1101110 )
1(
1!
#220
0(
0!
#221
b1101111 )
1(
1!
#222
0(
0!
#223
b1110000 )
1(
1!
#224
0(
0!
#225
b1110001 )
1(
1!
#226
0(
0!
#227
b1110010 )
1(
1!
#228
0(
0!
#229
b1110011 )
1(
1!
#230
0(
0!
#231
b1110100 )
1(
1!
#232
0(
0!
#233
b1110101 )
1(
1!
#234
0(
0!
#235
b1110110 )
1(
1!
#236
0(
0!
#237
b1110111 )
1(
1!
#238
0(
0!
#239
b1111000 )
1(
1!
#240
0(
0!
#241
b1111001 )
1(
1!
#242
0(
0!
#243
b1111010 )
1(
1!
#244
0(
0!
#245
b1111011 )
1(
1!
#246
0(
0!
#247
b1111100 )
1(
1!
#248
0(
0!
#249
b1111101 )
1(
1!
#250
0(
0!
#251
b1111110 )
1(
1!
#252
0(
0!
#253
b1111111 )
1(
1!
#254
0(
0!
#255
b10000000 )
1(
1!
#256
0(
0!
#257
b10000001 )
1(
1!
#258
0(
0!
#259
b10000010 )
1(
1!
#260
0(
0!
#261
b10000011 )
1(
1!
#262
0(
0!
#263
b10000100 )
1(
1!
#264
0(
0!
#265
b10000101 )
1(
1!
#266
0(
0!
#267
b10000110 )
1(
1!
#268
0(
0!
#269
b10000111 )
1(
1!
#270
0(
0!
#271
b10001000 )
1(
1!
#272
0(
0!
#273
b10001001 )
1(
1!
#274
0(
0!
#275
b10001010 )
1(
1!
#276
0(
0!
#277
b10001011 )
1(
1!
#278
0(
0!
#279
b10001100 )
1(
1!
#280
0(
0!
#281
b10001101 )
1(
1!
#282
0(
0!
#283
b10001110 )
1(
1!
#284
0(
0!
#285
b10001111 )
1(
1!
#286
0(
0!
#287
b10010000 )
1(
1!
#288
0(
0!
#289
b10010001 )
1(
1!
#290
0(
0!
#291
b10010010 )
1(
1!
#292
0(
0!
#293
b10010011 )
1(
1!
#294
0(
0!
#295
b10010100 )
1(
1!
#296
0(
0!
#297
b10010101 )
1(
1!
#298
0(
0!
#299
b10010110 )
1(
1!
#300
0(
0!
#301
b10010111 )
1(
1!
#302
0(
0!
#303
b10011000 )
1(
1!
#304
0(
0!
#305
b10011001 )
1(
1!
#306
0(
0!
#307
b10011010 )
1(
1!
#308
0(
0!
#309
b10011011 )
1(
1!
#310
0(
0!
#311
b10011100 )
1(
1!
#312
0(
0!
#313
b10011101 )
1(
1!
#314
0(
0!
#315
b10011110 )
1(
1!
#316
0(
0!
#317
b10011111 )
1(
1!
#318
0(
0!
#319
b10100000 )
1(
1!
#320
0(
0!
#321
b10100001 )
1(
1!
#322
0(
0!
#323
b10100010 )
1(
1!
#324
0(
0!
#325
b10100011 )
1(
1!
#326
0(
0!
#327
b10100100 )
1(
1!
#328
0(
0!
#329
b10100101 )
1(
1!
#330
0(
0!
#331
b10100110 )
1(
1!
#332
0(
0!
#333
b10100111 )
1(
1!
#334
0(
0!
#335
b10101000 )
1(
1!
#336
0(
0!
#337
b10101001 )
1(
1!
#338
0(
0!
#339
b10101010 )
1(
1!
#340
0(
0!
#341
b10101011 )
1(
1!
#342
0(
0!
#343
b10101100 )
1(
1!
#344
0(
0!
#345
b10101101 )
1(
1!
#346
0(
0!
#347
b10101110 )
1(
1!
#348
0(
0!
#349
b10101111 )
1(
1!
#350
0(
0!
#351
b10110000 )
1(
1!
#352
0(
0!
#353
b10110001 )
1(
1!
#354
0(
0!
#355
b10110010 )
1(
1!
#356
0(
0!
#357
b10110011 )
1(
1!
#358
0(
0!
#359
b10110100 )
1(
1!
#360
0(
0!
#361
b10110101 )
1(
1!
#362
0(
0!
#363
b10110110 )
1(
1!
#364
0(
0!
#365
b10110111 )
1(
1!
#366
0(
0!
#367
b10111000 )
1(
1!
#368
0(
0!
#369
b10111001 )
1(
1!
#370
0(
0!
#371
b10111010 )
1(
1!
#372
0(
0!
#373
b10111011 )
1(
1!
#374
0(
0!
#375
b10111100 )
1(
1!
#376
0(
0!
#377
b10111101 )
1(
1!
#378
0(
0!
#379
b10111110 )
1(
1!
#380
0(
0!
#381
b10111111 )
1(
1!
#382
0(
0!
#383
b11000000 )
1(
1!
#384
0(
0!
#385
b11000001 )
1(
1!
#386
0(
0!
#387
b11000010 )
1(
1!
#388
0(
0!
#389
b11000011 )
1(
1!
#390
0(
0!
#391
b11000100 )
1(
1!
#392
0(
0!
#393
b11000101 )
1(
1!
#394
0(
0!
#395
b11000110 )
1(
1!
#396
0(
0!
#397
b11000111 )
1(
1!
#398
0(
0!
#399
b11001000 )
1(
1!
#400
0(
0!
#401
b11001001 )
1(
1!
#402
0(
0!
#403
b11001010 )
1(
1!
#404
0(
0!
#405
b11001011 )
1(
1!
#406
0(
0!
#407
b11001100 )
1(
1!
#408
0(
0!
#409
b11001101 )
1(
1!
#410
0(
0!
#411
b11001110 )
1(
1!
#412
0(
0!
#413
b11001111 )
1(
1!
#414
0(
0!
#415
b11010000 )
1(
1!
#416
0(
0!
#417
b11010001 )
1(
1!
#418
0(
0!
#419
b11010010 )
1(
1!
#420
0(
0!
#421
b11010011 )
1(
1!
#422
0(
0!
#423
b11010100 )
1(
1!
#424
0(
0!
#425
b11010101 )
1(
1!
#426
0(
0!
#427
b11010110 )
1(
1!
#428
0(
0!
#429
b11010111 )
1(
1!
#430
0(
0!
#431
b11011000 )
1(
1!
#432
0(
0!
#433
b11011001 )
1(
1!
#434
0(
0!
#435
b11011010 )
1(
1!
#436
0(
0!
#437
b11011011 )
1(
1!
#438
0(
0!
#439
b11011100 )
1(
1!
#440
0(
0!
#441
b11011101 )
1(
1!
#442
0(
0!
#443
b11011110 )
1(
1!
#444
0(
0!
#445
b11011111 )
1(
1!
#446
0(
0!
#447
b11100000 )
1(
1!
#448
0(
0!
#449
b11100001 )
1(
1!
#450
0(
0!
#451
b11100010 )
1(
1!
#452
0(
0!
#453
b11100011 )
1(
1!
#454
0(
0!
#455
b11100100 )
1(
1!
#456
0(
0!
#457
b11100101 )
1(
1!
#458
0(
0!
#459
b11100110 )
1(
1!
#460
0(
0!
#461
b11100111 )
1(
1!
#462
0(
0!
#463
b11101000 )
1(
1!
#464
0(
0!
#465
b11101001 )
1(
1!
#466
0(
0!
#467
b11101010 )
1(
1!
#468
0(
0!
#469
b11101011 )
1(
1!
#470
0(
0!
#471
b11101100 )
1(
1!
#472
0(
0!
#473
b11101101 )
1(
1!
#474
0(
0!
#475
b11101110 )
1(
1!
#476
0(
0!
#477
b11101111 )
1(
1!
#478
0(
0!
#479
b11110000 )
1(
1!
#480
0(
0!
#481
b11110001 )
1(
1!
#482
0(
0!
#483
b11110010 )
1(
1!
#484
0(
0!
#485
b11110011 )
1(
1!
#486
0(
0!
#487
b11110100 )
1(
1!
#488
0(
0!
#489
b11110101 )
1(
1!
#490
0(
0!
#491
b11110110 )
1(
1!
#492
0(
0!
#493
b11110111 )
1(
1!
#494
0(
0!
#495
b11111000 )
1(
1!
#496
0(
0!
#497
b11111001 )
1(
1!
#498
0(
0!
#499
b11111010 )
1(
1!
#500
0(
0!
#501
b11111011 )
1(
1!
#502
0(
0!
#503
b11111100 )
1(
1!
#504
0(
0!
#505
b11111101 )
1(
1!
#506
0(
0!
#507
b11111110 )
1(
1!
#508
0(
0!
#509
b11111111 )
1(
1!
#510
0(
0!
#511
b100000000 )
1(
1!
#512
0(
0!
#513
b100000001 )
1(
1!
#514
0(
0!
#515
b100000010 )
1(
1!
#516
0(
0!
#517
b100000011 )
1(
1!
#518
0(
0!
#519
b100000100 )
1(
1!
#520
0(
0!
#521
b100000101 )
1(
1!
#522
0(
0!
#523
b100000110 )
1(
1!
#524
0(
0!
#525
b100000111 )
1(
1!
#526
0(
0!
#527
b100001000 )
1(
1!
#528
0(
0!
#529
b100001001 )
1(
1!
#530
0(
0!
#531
b100001010 )
1(
1!
#532
0(
0!
#533
b100001011 )
1(
1!
#534
0(
0!
#535
b100001100 )
1(
1!
#536
0(
0!
#537
b100001101 )
1(
1!
#538
0(
0!
#539
b100001110 )
1(
1!
#540
0(
0!
#541
b100001111 )
1(
1!
#542
0(
0!
#543
b100010000 )
1(
1!
#544
0(
0!
#545
b100010001 )
1(
1!
#546
0(
0!
#547
b100010010 )
1(
1!
#548
0(
0!
#549
b100010011 )
1(
1!
#550
0(
0!
#551
b100010100 )
1(
1!
#552
0(
0!
#553
b100010101 )
1(
1!
#554
0(
0!
#555
b100010110 )
1(
1!
#556
0(
0!
#557
b100010111 )
1(
1!
#558
0(
0!
#559
b100011000 )
1(
1!
#560
0(
0!
#561
b100011001 )
1(
1!
#562
0(
0!
#563
b100011010 )
1(
1!
#564
0(
0!
#565
b100011011 )
1(
1!
#566
0(
0!
#567
b100011100 )
1(
1!
#568
0(
0!
#569
b100011101 )
1(
1!
#570
0(
0!
#571
b100011110 )
1(
1!
#572
0(
0!
#573
b100011111 )
1(
1!
#574
0(
0!
#575
b100100000 )
1(
1!
#576
0(
0!
#577
b100100001 )
1(
1!
#578
0(
0!
#579
b100100010 )
1(
1!
#580
0(
0!
#581
b100100011 )
1(
1!
#582
0(
0!
#583
b100100100 )
1(
1!
#584
0(
0!
#585
b100100101 )
1(
1!
#586
0(
0!
#587
b100100110 )
1(
1!
#588
0(
0!
#589
b100100111 )
1(
1!
#590
0(
0!
#591
b100101000 )
1(
1!
#592
0(
0!
#593
b100101001 )
1(
1!
#594
0(
0!
#595
b100101010 )
1(
1!
#596
0(
0!
#597
b100101011 )
1(
1!
#598
0(
0!
#599
b100101100 )
1(
1!
#600
0(
0!
#601
b100101101 )
1(
1!
#602
0(
0!
#603
b100101110 )
1(
1!
#604
0(
0!
#605
b100101111 )
1(
1!
#606
0(
0!
#607
b100110000 )
1(
1!
#608
0(
0!
#609
b100110001 )
1(
1!
#610
0(
0!
#611
b100110010 )
1(
1!
#612
0(
0!
#613
b100110011 )
1(
1!
#614
0(
0!
#615
b100110100 )
1(
1!
#616
0(
0!
#617
b100110101 )
1(
1!
#618
0(
0!
#619
b100110110 )
1(
1!
#620
0(
0!
#621
b100110111 )
1(
1!
#622
0(
0!
#623
b100111000 )
1(
1!
#624
0(
0!
#625
b100111001 )
1(
1!
#626
0(
0!
#627
b100111010 )
1(
1!
#628
0(
0!
#629
b100111011 )
1(
1!
#630
0(
0!
#631
b100111100 )
1(
1!
#632
0(
0!
#633
b100111101 )
1(
1!
#634
0(
0!
#635
b100111110 )
1(
1!
#636
0(
0!
#637
b100111111 )
1(
1!
#638
0(
0!
#639
b101000000 )
1(
1!
#640
0(
0!
#641
b101000001 )
1(
1!
#642
0(
0!
#643
b101000010 )
1(
1!
#644
0(
0!
#645
b101000011 )
1(
1!
#646
0(
0!
#647
b101000100 )
1(
1!
#648
0(
0!
#649
b101000101 )
1(
1!
#650
0(
0!
#651
b101000110 )
1(
1!
#652
0(
0!
#653
b101000111 )
1(
1!
#654
0(
0!
#655
b101001000 )
1(
1!
#656
0(
0!
#657
b101001001 )
1(
1!
#658
0(
0!
#659
b101001010 )
1(
1!
#660
0(
0!
#661
b101001011 )
1(
1!
#662
0(
0!
#663
b101001100 )
1(
1!
#664
0(
0!
#665
b101001101 )
1(
1!
#666
0(
0!
#667
b101001110 )
1(
1!
#668
0(
0!
#669
b101001111 )
1(
1!
#670
0(
0!
#671
b101010000 )
1(
1!
#672
0(
0!
#673
b101010001 )
1(
1!
#674
0(
0!
#675
b101010010 )
1(
1!
#676
0(
0!
#677
b101010011 )
1(
1!
#678
0(
0!
#679
b101010100 )
1(
1!
#680
0(
0!
#681
b101010101 )
1(
1!
#682
0(
0!
#683
b101010110 )
1(
1!
#684
0(
0!
#685
b101010111 )
1(
1!
#686
0(
0!
#687
b101011000 )
1(
1!
#688
0(
0!
#689
b101011001 )
1(
1!
#690
0(
0!
#691
b101011010 )
1(
1!
#692
0(
0!
#693
b101011011 )
1(
1!
#694
0(
0!
#695
b101011100 )
1(
1!
#696
0(
0!
#697
b101011101 )
1(
1!
#698
0(
0!
#699
b101011110 )
1(
1!
#700
0(
0!
#701
b101011111 )
1(
1!
#702
0(
0!
#703
b101100000 )
1(
1!
#704
0(
0!
#705
b101100001 )
1(
1!
#706
0(
0!
#707
b101100010 )
1(
1!
#708
0(
0!
#709
b101100011 )
1(
1!
#710
0(
0!
#711
b101100100 )
1(
1!
#712
0(
0!
#713
b101100101 )
1(
1!
#714
0(
0!
#715
b101100110 )
1(
1!
#716
0(
0!
#717
b101100111 )
1(
1!
#718
0(
0!
#719
b101101000 )
1(
1!
#720
0(
0!
#721
b101101001 )
1(
1!
#722
0(
0!
#723
b101101010 )
1(
1!
#724
0(
0!
#725
b101101011 )
1(
1!
#726
0(
0!
#727
b101101100 )
1(
1!
#728
0(
0!
#729
b101101101 )
1(
1!
#730
0(
0!
#731
b101101110 )
1(
1!
#732
0(
0!
#733
b101101111 )
1(
1!
#734
0(
0!
#735
b101110000 )
1(
1!
#736
0(
0!
#737
b101110001 )
1(
1!
#738
0(
0!
#739
b101110010 )
1(
1!
#740
0(
0!
#741
b101110011 )
1(
1!
#742
0(
0!
#743
b101110100 )
1(
1!
#744
0(
0!
#745
b101110101 )
1(
1!
#746
0(
0!
#747
b101110110 )
1(
1!
#748
0(
0!
#749
b101110111 )
1(
1!
#750
0(
0!
#751
b101111000 )
1(
1!
#752
0(
0!
#753
b101111001 )
1(
1!
#754
0(
0!
#755
b101111010 )
1(
1!
#756
0(
0!
#757
b101111011 )
1(
1!
#758
0(
0!
#759
b101111100 )
1(
1!
#760
0(
0!
#761
b101111101 )
1(
1!
#762
0(
0!
#763
b101111110 )
1(
1!
#764
0(
0!
#765
b101111111 )
1(
1!
#766
0(
0!
#767
b110000000 )
1(
1!
#768
0(
0!
#769
b110000001 )
1(
1!
#770
0(
0!
#771
b110000010 )
1(
1!
#772
0(
0!
#773
b110000011 )
1(
1!
#774
0(
0!
#775
b110000100 )
1(
1!
#776
0(
0!
#777
b110000101 )
1(
1!
#778
0(
0!
#779
b110000110 )
1(
1!
#780
0(
0!
#781
b110000111 )
1(
1!
#782
0(
0!
#783
b110001000 )
1(
1!
#784
0(
0!
#785
b110001001 )
1(
1!
#786
0(
0!
#787
b110001010 )
1(
1!
#788
0(
0!
#789
b110001011 )
1(
1!
#790
0(
0!
#791
b110001100 )
1(
1!
#792
0(
0!
#793
b110001101 )
1(
1!
#794
0(
0!
#795
b110001110 )
1(
1!
#796
0(
0!
#797
b110001111 )
1(
1!
#798
0(
0!
#799
b110010000 )
1(
1!
#800
0(
0!
#801
b110010001 )
1(
1!
#802
0(
0!
#803
b110010010 )
1(
1!
#804
0(
0!
#805
b110010011 )
1(
1!
#806
0(
0!
#807
b110010100 )
1(
1!
#808
0(
0!
#809
b110010101 )
1(
1!
#810
0(
0!
#811
b110010110 )
1(
1!
#812
0(
0!
#813
b110010111 )
1(
1!
#814
0(
0!
#815
b110011000 )
1(
1!
#816
0(
0!
#817
b110011001 )
1(
1!
#818
0(
0!
#819
b110011010 )
1(
1!
#820
0(
0!
#821
b110011011 )
1(
1!
#822
0(
0!
#823
b110011100 )
1(
1!
#824
0(
0!
#825
b110011101 )
1(
1!
#826
0(
0!
#827
b110011110 )
1(
1!
#828
0(
0!
#829
b110011111 )
1(
1!
#830
0(
0!
#831
b110100000 )
1(
1!
#832
0(
0!
#833
b110100001 )
1(
1!
#834
0(
0!
#835
b110100010 )
1(
1!
#836
0(
0!
#837
b110100011 )
1(
1!
#838
0(
0!
#839
b110100100 )
1(
1!
#840
0(
0!
#841
b110100101 )
1(
1!
#842
0(
0!
#843
b110100110 )
1(
1!
#844
0(
0!
#845
b110100111 )
1(
1!
#846
0(
0!
#847
b110101000 )
1(
1!
#848
0(
0!
#849
b110101001 )
1(
1!
#850
0(
0!
#851
b110101010 )
1(
1!
#852
0(
0!
#853
b110101011 )
1(
1!
#854
0(
0!
#855
b110101100 )
1(
1!
#856
0(
0!
#857
b110101101 )
1(
1!
#858
0(
0!
#859
b110101110 )
1(
1!
#860
0(
0!
#861
b110101111 )
1(
1!
#862
0(
0!
#863
b110110000 )
1(
1!
#864
0(
0!
#865
b110110001 )
1(
1!
#866
0(
0!
#867
b110110010 )
1(
1!
#868
0(
0!
#869
b110110011 )
1(
1!
#870
0(
0!
#871
b110110100 )
1(
1!
#872
0(
0!
#873
b110110101 )
1(
1!
#874
0(
0!
#875
b110110110 )
1(
1!
#876
0(
0!
#877
b110110111 )
1(
1!
#878
0(
0!
#879
b110111000 )
1(
1!
#880
0(
0!
#881
b110111001 )
1(
1!
#882
0(
0!
#883
b110111010 )
1(
1!
#884
0(
0!
#885
b110111011 )
1(
1!
#886
0(
0!
#887
b110111100 )
1(
1!
#888
0(
0!
#889
b110111101 )
1(
1!
#890
0(
0!
#891
b110111110 )
1(
1!
#892
0(
0!
#893
b110111111 )
1(
1!
#894
0(
0!
#895
b111000000 )
1(
1!
#896
0(
0!
#897
b111000001 )
1(
1!
#898
0(
0!
#899
b111000010 )
1(
1!
#900
0(
0!
#901
b111000011 )
1(
1!
#902
0(
0!
#903
b111000100 )
1(
1!
#904
0(
0!
#905
b111000101 )
1(
1!
#906
0(
0!
#907
b111000110 )
1(
1!
#908
0(
0!
#909
b111000111 )
1(
1!
